graphscope/flex/rest/__init__.py
graphscope/flex/rest/api_client.py
graphscope/flex/rest/api_response.py
graphscope/flex/rest/configuration.py
graphscope/flex/rest/exceptions.py
graphscope/flex/rest/py.typed
graphscope/flex/rest/rest.py
graphscope/flex/rest/api/__init__.py
graphscope/flex/rest/api/alert_api.py
graphscope/flex/rest/api/data_source_api.py
graphscope/flex/rest/api/deployment_api.py
graphscope/flex/rest/api/graph_api.py
graphscope/flex/rest/api/job_api.py
graphscope/flex/rest/api/service_api.py
graphscope/flex/rest/api/stored_procedure_api.py
graphscope/flex/rest/api/utils_api.py
graphscope/flex/rest/models/__init__.py
graphscope/flex/rest/models/base_edge_type.py
graphscope/flex/rest/models/base_edge_type_vertex_type_pair_relations_inner.py
graphscope/flex/rest/models/base_edge_type_vertex_type_pair_relations_inner_x_csr_params.py
graphscope/flex/rest/models/base_property_meta.py
graphscope/flex/rest/models/base_vertex_type.py
graphscope/flex/rest/models/base_vertex_type_x_csr_params.py
graphscope/flex/rest/models/column_mapping.py
graphscope/flex/rest/models/column_mapping_column.py
graphscope/flex/rest/models/create_alert_receiver_request.py
graphscope/flex/rest/models/create_alert_rule_request.py
graphscope/flex/rest/models/create_dataloading_job_response.py
graphscope/flex/rest/models/create_edge_type.py
graphscope/flex/rest/models/create_graph_request.py
graphscope/flex/rest/models/create_graph_response.py
graphscope/flex/rest/models/create_graph_schema_request.py
graphscope/flex/rest/models/create_property_meta.py
graphscope/flex/rest/models/create_stored_proc_request.py
graphscope/flex/rest/models/create_stored_proc_response.py
graphscope/flex/rest/models/create_vertex_type.py
graphscope/flex/rest/models/dataloading_job_config.py
graphscope/flex/rest/models/dataloading_job_config_edges_inner.py
graphscope/flex/rest/models/dataloading_job_config_loading_config.py
graphscope/flex/rest/models/dataloading_job_config_loading_config_format.py
graphscope_flex-0.31.0.dist-info/METADATA
graphscope_flex-0.31.0.dist-info/WHEEL
graphscope_flex-0.31.0.dist-info/top_level.txt
graphscope_flex-0.31.0.dist-info/RECORD
