Metadata-Version: 2.1
Name: graphscope-flex
Version: 0.31.0
Summary: GraphScope FLEX HTTP SERVICE API
Home-page: UNKNOWN
Author: GraphScope
Author-email: graphscope@alibaba-inc.com
License: Apache 2.0
Keywords: OpenAPI,OpenAPI-Generator,GraphScope FLEX HTTP SERVICE API
Platform: UNKNOWN
Requires-Dist: pydantic (>=2)
Requires-Dist: python-dateutil
Requires-Dist: typing-extensions (>=4.7.1)
Requires-Dist: urllib3 (<2.1.0,>=1.25.3)
